tachypy/__init__.py
tachypy/audio.py
tachypy/psychophysics.py
tachypy/quest.py
tachypy/responses.py
tachypy/screen.py
tachypy/shapes.py
tachypy/text.py
tachypy/textures.py
tachypy-0.1.2.dist-info/LICENSE
tachypy-0.1.2.dist-info/METADATA
tachypy-0.1.2.dist-info/WHEEL
tachypy-0.1.2.dist-info/top_level.txt
tachypy-0.1.2.dist-info/RECORD
