Metadata-Version: 2.1
Name: tachypy
Version: 0.1.2
Summary: A package for OpenGL drawing using Pygame.
Home-page: https://github.com/CharestLab/tachypy
Author: Ian Charest and Frederic Gosselin
Author-email: charest.ian@gmail.com
License: MIT
Classifier: Programming Language :: Python :: 3
Classifier: Programming Language :: Python :: 3.6
Classifier: Programming Language :: Python :: 3.7
Classifier: Programming Language :: Python :: 3.8
Classifier: Programming Language :: Python :: 3.9
Classifier: Programming Language :: Python :: 3.10
Classifier: Programming Language :: Python :: 3.11
Classifier: Operating System :: OS Independent
Requires-Python: >=3.6
License-File: LICENSE
Requires-Dist: numpy>=1.18.0
Requires-Dist: pygame>=2.0.0
Requires-Dist: PyOpenGL>=3.1.0
Requires-Dist: screeninfo>=0.6.0
Requires-Dist: sounddevice
